pysuit/__init__.py
pysuit/interface.py
pysuit/modules/__init__.py
pysuit/modules/dict_collection.py
pysuit/modules/exclude_random.py
pysuit/modules/nested_iterator.py
pysuit/modules/random_datatype_collection.py
pysuit-1.0.1.dist-info/LICENSE
pysuit-1.0.1.dist-info/WHEEL
pysuit-1.0.1.dist-info/METADATA
pysuit-1.0.1.dist-info/RECORD
