Metadata-Version: 2.1
Name: pysuit
Version: 1.0.1
Summary: This package will resolve all small intigrities of python data structures(List,Tuple,Dictionary,Set) which are not provided by-default.
Home-page: https://github.com/deep-tw/py-suit.git
License: MIT
Keywords: py-suite,suite,python bugs,features,py-features
Author: Avinash Tiwari
Author-email: avinash@thoughtwin.com
Requires-Python: >=3.7.0
Classifier: License :: OSI Approved :: MIT License
Classifier: Operating System :: OS Independent
Classifier: Programming Language :: Python :: 3
Classifier: Programming Language :: Python :: 3.10
Classifier: Programming Language :: Python :: 3.6
Classifier: Programming Language :: Python :: 3.7
Classifier: Programming Language :: Python :: 3.8
Classifier: Programming Language :: Python :: 3.9
Project-URL: Repository, https://github.com/deep-tw/py-suit.git
